conventional_commits_check/__init__.py
conventional_commits_check/commit_types.py
conventional_commits_check/main.py
test/__init__.py
test/test_main.py
conventional_commits_check-2.9.0.dist-info/LICENSE
conventional_commits_check-2.9.0.dist-info/METADATA
conventional_commits_check-2.9.0.dist-info/WHEEL
conventional_commits_check-2.9.0.dist-info/entry_points.txt
conventional_commits_check-2.9.0.dist-info/top_level.txt
conventional_commits_check-2.9.0.dist-info/RECORD
