Metadata-Version: 2.1
Name: conventional-commits-check
Version: 2.9.0
Summary: A pre-commit hook to check Conventional Commits and add emojis.
Home-page: https://github.com/AliYmn/conventional-commits-check
Author: Ali Yaman
License: MIT
Classifier: Development Status :: 3 - Alpha
Classifier: Environment :: Console
Classifier: Intended Audience :: Developers
Classifier: License :: OSI Approved :: MIT License
Classifier: Operating System :: OS Independent
Classifier: Programming Language :: Python :: 3
Classifier: Programming Language :: Python :: 3.6
Classifier: Programming Language :: Python :: 3.7
Classifier: Programming Language :: Python :: 3.8
Classifier: Programming Language :: Python :: 3.9
Classifier: Programming Language :: Python :: 3.10
Classifier: Programming Language :: Python :: 3.11
Classifier: Programming Language :: Python :: 3.12
Classifier: Programming Language :: Python :: 3.13
Classifier: Topic :: Software Development :: Version Control
Classifier: Topic :: Utilities
License-File: LICENSE
Requires-Dist: pyyaml ==6.0.2
